README.md
setup.py
pyterm_progress_bar/__init__.py
pyterm_progress_bar.egg-info/PKG-INFO
pyterm_progress_bar.egg-info/SOURCES.txt
pyterm_progress_bar.egg-info/dependency_links.txt
pyterm_progress_bar.egg-info/top_level.txt