Metadata-Version: 2.1
Name: pyterm-progress-bar
Version: 0.0.1
Summary: Prints a progress bar to the terminal from python.
Home-page: https://github.com/wpbdry/pyterm_progress_bar_pkg
Author: William Dry
Author-email: wpbdry@gmail.com
License: MIT
Platform: UNKNOWN
Classifier: Programming Language :: Python :: 3
Classifier: License :: OSI Approved :: MIT License
Classifier: Operating System :: OS Independent
